__init__.py
inu.py
inu-2.5.6.dist-info/licenses/LICENSE.txt
inu-2.5.6.dist-info/METADATA
inu-2.5.6.dist-info/WHEEL
inu-2.5.6.dist-info/top_level.txt
inu-2.5.6.dist-info/RECORD
