Metadata-Version: 2.4
Name: inu
Version: 2.5.6
Summary: Inertial Navigation Utilities
Author-email: David Woodburn <david.woodburn@icloud.com>
License-Expression: MIT
Project-URL: Homepage, https://gitlab.com/davidwoodburn/inu
Project-URL: Bug Tracker, https://gitlab.com/davidwoodburn/inu/-/issues
Classifier: Programming Language :: Python :: 3
Classifier: Operating System :: OS Independent
Requires-Python: >=3.6
License-File: LICENSE.txt
Requires-Dist: numpy
Requires-Dist: scipy
Requires-Dist: matplotlib
Requires-Dist: r3f
Provides-Extra: test
Requires-Dist: pytest; extra == "test"
Requires-Dist: avar; extra == "test"
Dynamic: license-file
